ideadensity/__init__.py
ideadensity/depid.py
ideadensity/idea_density_rater.py
ideadensity/idea_density_rater_rules.py
ideadensity/tagger.py
ideadensity/utils/constants.py
ideadensity/utils/export_utils.py
ideadensity/utils/version_utils.py
ideadensity/utils/word_search_utils.py
ideadensity/word_item.py
ideadensity-0.5.1.dist-info/LICENSE
ideadensity-0.5.1.dist-info/METADATA
ideadensity-0.5.1.dist-info/WHEEL
ideadensity-0.5.1.dist-info/RECORD
