Metadata-Version: 2.1
Name: ideadensity
Version: 0.5.1
Summary: Python library for computing propositional idea density
Home-page: https://github.com/jrrobison1/ideadensity
License: GNU GPLv2
Keywords: nlp,idea density,linguistics
Author: Jason Robison
Author-email: jrrobison@protonmail.com
Requires-Python: >=3.10,<3.13
Classifier: Development Status :: 3 - Alpha
Classifier: Intended Audience :: Developers
Classifier: License :: OSI Approved :: GNU General Public License v2 (GPLv2)
Classifier: License :: Other/Proprietary License
Classifier: Programming Language :: Python :: 3
Classifier: Programming Language :: Python :: 3.10
Classifier: Programming Language :: Python :: 3.11
Classifier: Programming Language :: Python :: 3.12
Requires-Dist: pyqt6 (>=6.6.1,<7.0.0)
Requires-Dist: python-levenshtein (>=0.25.1,<0.26.0)
Requires-Dist: spacy (>=3.8.4,<4.0.0)
Requires-Dist: tomli (>=2.2.1,<3.0.0)
Project-URL: Repository, https://github.com/jrrobison1/ideadensity
